domishot/__init__.py
domishot/cli.py
domishot/core.py
domishot-0.1.2.dist-info/METADATA
domishot-0.1.2.dist-info/WHEEL
domishot-0.1.2.dist-info/entry_points.txt
domishot-0.1.2.dist-info/top_level.txt
domishot-0.1.2.dist-info/RECORD
