Metadata-Version: 2.4
Name: domishot
Version: 0.1.2
Summary: Capture a specific DOM element from any web page as an image (Playwright-first, Selenium fallback).
Author: Eric Moral
License-Expression: MIT
Project-URL: Homepage, https://github.com/nusiko/domishot
Project-URL: Repository, https://github.com/nusiko/domishot
Project-URL: Issues, https://github.com/nusiko/domishot/issues
Project-URL: Changelog, https://github.com/nusiko/domishot/releases
Keywords: screenshot,playwright,selenium,automation,web
Classifier: Programming Language :: Python :: 3
Classifier: Operating System :: OS Independent
Requires-Python: >=3.9
Provides-Extra: playwright
Requires-Dist: playwright>=1.45; extra == "playwright"
Provides-Extra: selenium
Requires-Dist: selenium>=4.12; extra == "selenium"
Requires-Dist: webdriver-manager>=4.0; extra == "selenium"
